base_client_api/__init__.py
base_client_api/base_client.py
base_client_api/exceptions.py
base_client_api/models/__init__.py
base_client_api/models/base.py
base_client_api/models/record.py
base_client_api/models/results.py
base_client_api/utils.py
base_client_api-2.4.1.dist-info/LICENSE.md
base_client_api-2.4.1.dist-info/WHEEL
base_client_api-2.4.1.dist-info/METADATA
base_client_api-2.4.1.dist-info/RECORD
