Metadata-Version: 2.1
Name: base-client-api
Version: 2.4.1
Summary: Base Client API; Used to build other client APIs
Author: Jerod Gawne
Author-email: jerodgawne@gmail.com
Requires-Python: >=3.9.0,<4.0.0
Classifier: Programming Language :: Python :: 3
Classifier: Programming Language :: Python :: 3.9
Requires-Dist: aiodns (>=3.0.0,<4.0.0)
Requires-Dist: aiofiles (>=0.6.0,<0.7.0)
Requires-Dist: aiohttp (>=3.7.4,<4.0.0)
Requires-Dist: aiohttp-pydantic (>=1.9.0,<2.0.0)
Requires-Dist: brotlipy (>=0.7.0,<0.8.0)
Requires-Dist: cchardet (>=2.1.7,<3.0.0)
Requires-Dist: loguru (>=0.5.3,<0.6.0)
Requires-Dist: python-rapidjson (>=1.0,<2.0)
Requires-Dist: rich (>=10.1.0,<11.0.0)
Requires-Dist: tenacity (>=7.0.0,<8.0.0)
Requires-Dist: toml (>=0.10.2,<0.11.0)
Requires-Dist: uvloop (>=0.15.2,<0.16.0)
